{
    "backend": {
        "usersDbUrl": "../db/data.json"
    },
    "startParams": {
        "activeMonth": 4,
        "activeYear": 2021
    },
    "initialStates": {
        "initDb": {
            "initData": [],
            "initStatus": null,
            "initError": null
        },
        "initStatOnPage": {
            "initSortingDataArr": null,
            "initDataOnPage": null,
            "initRowOnPage": 10,
            "initActivePage": 1,
            "initSortColumn": "userName",
            "initDirectSort": true,
            "initActiveMonth": 0,
            "initActiveYear": 0,
            "initDaysInActiveMonth": 0,
            "initUsersCount": 0
        },
        "initSortParam": {
            "initSortColumn": "userName",
            "initDirectSort": true
        }
    }
}